[{"$i":"select-wallpaper","$v":"वालपेपर चयन गर्नुहोस"},{"$i":"cancel","$v":"रद्द गर्नुहोस्"},{"$i":"set-wallpaper","$v":"सेट गर्नुहोस्"},{"$i":"save","$v":"सुरक्षित गर्नुहोस्"},{"$i":"kai-wallpaper-set","$v":"वालपेपर सेट गर्नुहोस्"},{"$i":"wallpaper-not-changed","$v":"वालपेपर परिवर्तन गर्न सकिन्न"},{"$i":"dialog-title-action-disabled","$v":"कार्य अनुमति छैन"},{"$i":"dialog-body-action-disabled","$v":"यो कार्य निस्क्रिय गरिएको छ। थप पत्ता लगाउन, तपाईंको संस्थाको प्रशासनमा सम्पर्क गर्नुहोस्।"},{"$i":"dialog-button-ok","$v":"ठीक छ"}]