[{"$i":"filemanager","$v":"Menadžer datoteka"},{"$i":"internal","$v":"Interno"},{"$i":"sdcard","$v":"SD kartica"},{"$i":"no-files","$v":"Ovaj folder je prazan."},{"$i":"not-support-header","$v":"Nije moguće otvoriti"},{"$i":"not-support-content","$v":"Ovaj format datoteke je nevažeći ili nije podržan."},{"$i":"confirmation-header","$v":"Potvrda"},{"$i":"delete-file-content","$v":["Obriši datoteku ",{"t":"idOrVar","v":"fileName"},"?"]},{"$i":"delete-folder-content","$v":["Sve stavke u odabranom folderu biće obrisane. Obriši folder ",{"t":"idOrVar","v":"fileName"},"?"]},{"$i":"copy-move-header","$v":"Izaberite ciljni folder"},{"$i":"number-selected","$v":{"few":[{"t":"idOrVar","v":"number"}," odabrana"],"many":[{"t":"idOrVar","v":"number"}," odabrana"],"one":[{"t":"idOrVar","v":"number"}," odabrana"],"other":[{"t":"idOrVar","v":"number"}," odabrana"],"two":[{"t":"idOrVar","v":"number"}," odabrana"],"zero":[{"t":"idOrVar","v":"number"}," odabrana"]},"$x":[{"t":"idOrVar","v":"plural"},"number"]},{"$i":"delete-all-folder","$v":"Sve stavke u odabranom folderu biće obrisane. Obriši odabrane stavke?"},{"$i":"delete-all-file","$v":"Obrisati odabrane stavke?"},{"$i":"search-in","$v":"Pretraživane u"},{"$i":"search-current","$v":"Samo trenutni folder"},{"$i":"search-internal","$v":"Interno"},{"$i":"search-sdcard","$v":"SD kartica"},{"$i":"search-header","$v":["Traži: ",{"t":"idOrVar","v":"keyword"}]},{"$i":"file-exist","$v":[{"t":"idOrVar","v":"fileName"}," već postoji na ovoj lokaciji. Zadrži obe stavke?"]},{"$i":"paste-error","$v":"Ne možete nalepiti folder u samog sebe."},{"$i":"move-error","$v":"Ne možete premestiti folder u samog sebe."},{"$i":"new-folder-error","$v":["Naziv ",{"t":"idOrVar","v":"folderName"}," je već zauzet. Izaberite drugi naziv."]},{"$i":"searching","$v":"Pretraga..."},{"$i":"loading","$v":"Učitavanje…"},{"$i":"search-empty","$v":"Nije nađeno"},{"$i":"new-folder-invalid","$v":["Naziv",{"t":"idOrVar","v":"folderName"}," je nevažeći. Izaberite drugi naziv."]},{"$i":"progress-head-copy","$v":"Kopiranje"},{"$i":"progress-content-copy","$v":"Kopiranje stavke"},{"$i":"progress-head-move","$v":"Premeštanje"},{"$i":"progress-content-move","$v":"Premeštanje stavke"},{"$i":"unsupport-folder-name","$v":{"$o":"Ne može da se koristi naziv sa nepodržanim znakovima: \\/:*?&quot;&lt;&gt;|"}},{"$i":"unsupport-string","$v":{"$o":["Nije moguće ",{"t":"idOrVar","v":"name"}," datoteku sa imenom koje sadrži nepodržane znakove: \\/:*?\"<>|"]}},{"$i":"not-enough-space","$v":"Nema dovoljno dostupnog prostora"},{"$i":"error-while-moving","$v":"Greška prilikom premeštanja"},{"$i":"error-while-copying","$v":"Greška prilikom kopiranja"},{"$i":"rename-not-suffix","$v":"Datoteka možda neće moći da se otvori posle promene oznake tipa datoteke. Ipak promeniti?"},{"$i":"open","$v":"Otvori"},{"$i":"options","$v":"Opcije"},{"$i":"ok","$v":"OK"},{"$i":"cancel","$v":"Otkaži"},{"$i":"change","$v":"Promeni"},{"$i":"paste","$v":"Nalepi"},{"$i":"select","$v":"Izaberi"},{"$i":"deselect","$v":"Poništi izbor"},{"$i":"replace","$v":"Zameni"},{"$i":"keep-both","$v":"Zadrži oba"},{"$i":"delete","$v":"Izbriši"},{"$i":"copy","$v":"Kopiraj"},{"$i":"move","$v":"Premesti"},{"$i":"rename","$v":"Preimenuj"},{"$i":"select-items","$v":"Odaberi stavke"},{"$i":"new-folder","$v":"Novi folder"},{"$i":"search","$v":"Traži"},{"$i":"refresh","$v":"Osveži"},{"$i":"details","$v":"Detalji"},{"$i":"share","$v":"Deli"},{"$i":"select-all","$v":"Odaberi sve"},{"$i":"deselect-all","$v":"Opozovi izbor svega"},{"$i":"detail-header","$v":"Detalji"},{"$i":"detail-name","$v":"Naziv"},{"$i":"detail-location","$v":"Lokacija"},{"$i":"detail-type","$v":"Tip"},{"$i":"detail-created","$v":"Kreirano"},{"$i":"detail-size","$v":"Veličina"},{"$i":"folder","$v":"folder"},{"$i":"type-unknow","$v":"nepoznato"},{"$i":"B","$v":"B"},{"$i":"KB","$v":"KB"},{"$i":"MB","$v":"MB"},{"$i":"GB","$v":"GB"},{"$i":"item-deleted","$v":"Ставка је избрисана."},{"$i":"items-deleted","$v":"Ставке су избрисане."},{"$i":"item-copied","$v":"Ставка је копирана."},{"$i":"items-copied","$v":"Ставке копиране."},{"$i":"item-moved","$v":"Ставка је премјештена."},{"$i":"items-moved","$v":"Ставке су премјештене."},{"$i":"file-renamed","$v":"Датотека је преименована."},{"$i":"folder-renamed","$v":"Фолдер ренамед."},{"$i":"folder-created","$v":"Фолдер цреатед."},{"$i":"refresh-completed","$v":"Osvežavanje je dovršeno."},{"$i":"itmes-not-copied","$v":["Nije kopirano ovoliko stavki: ",{"t":"idOrVar","v":"num"},"."]},{"$i":"itmes-not-moved","$v":["Nije premešteno ovoliko stavki: ",{"t":"idOrVar","v":"num"},"."]},{"$i":"weekday-0-long","$v":"Nedelja"},{"$i":"weekday-1-long","$v":"Ponedeljak"},{"$i":"weekday-2-long","$v":"Utorak"},{"$i":"weekday-3-long","$v":"Sreda"},{"$i":"weekday-4-long","$v":"Četvrtak"},{"$i":"weekday-5-long","$v":"Petak"},{"$i":"weekday-6-long","$v":"Subota"},{"$i":"weekday-0-short","$v":"Ned"},{"$i":"weekday-1-short","$v":"Pon"},{"$i":"weekday-2-short","$v":"Uto"},{"$i":"weekday-3-short","$v":"Sre"},{"$i":"weekday-4-short","$v":"Čet"},{"$i":"weekday-5-short","$v":"Pet"},{"$i":"weekday-6-short","$v":"Sub"},{"$i":"month-0-long","$v":"Januar"},{"$i":"month-1-long","$v":"Februar"},{"$i":"month-2-long","$v":"Mart"},{"$i":"month-3-long","$v":"April"},{"$i":"month-4-long","$v":"Maj"},{"$i":"month-5-long","$v":"Jun"},{"$i":"month-6-long","$v":"Jul"},{"$i":"month-7-long","$v":"Avgust"},{"$i":"month-8-long","$v":"Septembar"},{"$i":"month-9-long","$v":"Oktobar"},{"$i":"month-10-long","$v":"Novembar"},{"$i":"month-11-long","$v":"Decembar"},{"$i":"month-0-genitive","$v":"Januar"},{"$i":"month-1-genitive","$v":"Februar"},{"$i":"month-2-genitive","$v":"Mart"},{"$i":"month-3-genitive","$v":"April"},{"$i":"month-4-genitive","$v":"Maj"},{"$i":"month-5-genitive","$v":"Jun"},{"$i":"month-6-genitive","$v":"Jul"},{"$i":"month-7-genitive","$v":"Avgust"},{"$i":"month-8-genitive","$v":"Septembar"},{"$i":"month-9-genitive","$v":"Oktobar"},{"$i":"month-10-genitive","$v":"Novembar"},{"$i":"month-11-genitive","$v":"Decembar"},{"$i":"month-0-short","$v":"Jan"},{"$i":"month-1-short","$v":"Feb"},{"$i":"month-2-short","$v":"Mar"},{"$i":"month-3-short","$v":"Apr"},{"$i":"month-4-short","$v":"Maj"},{"$i":"month-5-short","$v":"Jun"},{"$i":"month-6-short","$v":"Jul"},{"$i":"month-7-short","$v":"Avg"},{"$i":"month-8-short","$v":"Sep"},{"$i":"month-9-short","$v":"Okt"},{"$i":"month-10-short","$v":"Nov"},{"$i":"month-11-short","$v":"Dec"},{"$i":"minutes-ago-long","$v":{"few":["Pre ",{"t":"idOrVar","v":"value"}," minuta"],"many":["Pre ",{"t":"idOrVar","v":"value"}," minuta"],"other":["Pre ",{"t":"idOrVar","v":"value"}," minuta"],"two":["Pre ",{"t":"idOrVar","v":"value"}," minuta"],"one":"pre jednog minuta","zero":"malopre"},"$x":[{"t":"idOrVar","v":"plural"},"value"]},{"$i":"hours-ago-long","$v":{"few":["Pre ovoliko sati: ",{"t":"idOrVar","v":"value"}],"many":["Pre ovoliko sati: ",{"t":"idOrVar","v":"value"}],"other":["Pre ovoliko sati: ",{"t":"idOrVar","v":"value"}],"two":["Pre ovoliko sati: ",{"t":"idOrVar","v":"value"}],"one":"пре 1 сат","zero":"malopre"},"$x":[{"t":"idOrVar","v":"plural"},"value"]},{"$i":"days-ago-long","$v":{"few":["Pre ",{"t":"idOrVar","v":"value"}," dana"],"many":["Pre ",{"t":"idOrVar","v":"value"}," dana"],"one":"juče","other":["Pre ",{"t":"idOrVar","v":"value"}," dana"],"two":["Pre ",{"t":"idOrVar","v":"value"}," dana"],"zero":"danas"},"$x":[{"t":"idOrVar","v":"plural"},"value"]},{"$i":"weeks-ago-long","$v":{"few":["Pre ovoliko nedelja: ",{"t":"idOrVar","v":"value"}],"many":["Pre ovoliko nedelja: ",{"t":"idOrVar","v":"value"}],"one":"prošle nedelje","other":["Pre ovoliko nedelja: ",{"t":"idOrVar","v":"value"}],"two":["Pre ovoliko nedelja: ",{"t":"idOrVar","v":"value"}],"zero":"ove nedelje"},"$x":[{"t":"idOrVar","v":"plural"},"value"]},{"$i":"months-ago-long","$v":{"few":["Pre ovoliko meseci: ",{"t":"idOrVar","v":"value"}],"many":["Pre ovoliko meseci: ",{"t":"idOrVar","v":"value"}],"one":"prošli mesec","other":["Pre ovoliko meseci: ",{"t":"idOrVar","v":"value"}],"two":["Pre ovoliko meseci: ",{"t":"idOrVar","v":"value"}],"zero":"ovog meseca"},"$x":[{"t":"idOrVar","v":"plural"},"value"]},{"$i":"years-ago-long","$v":{"few":["Pre ovoliko godina: ",{"t":"idOrVar","v":"value"}],"many":["Pre ovoliko godina: ",{"t":"idOrVar","v":"value"}],"one":"prošle godine","other":["Pre ovoliko godina: ",{"t":"idOrVar","v":"value"}],"two":["Pre ovoliko godina: ",{"t":"idOrVar","v":"value"}],"zero":"ove godine"},"$x":[{"t":"idOrVar","v":"plural"},"value"]},{"$i":"minutes-until-long","$v":{"few":["za ",{"t":"idOrVar","v":"value"}," minuta"],"many":["za ",{"t":"idOrVar","v":"value"}," minuta"],"other":["za ",{"t":"idOrVar","v":"value"}," minuta"],"two":["za ",{"t":"idOrVar","v":"value"}," minuta"],"zero":"sada","one":"за 1 минут"},"$x":[{"t":"idOrVar","v":"plural"},"value"]},{"$i":"hours-until-long","$v":{"few":["za ",{"t":"idOrVar","v":"value"}," sata/i"],"many":["za ",{"t":"idOrVar","v":"value"}," sata/i"],"other":["za ",{"t":"idOrVar","v":"value"}," sata/i"],"two":["za ",{"t":"idOrVar","v":"value"}," sata/i"],"zero":"sada","one":"за 1 сат"},"$x":[{"t":"idOrVar","v":"plural"},"value"]},{"$i":"days-until-long","$v":{"few":["za ",{"t":"idOrVar","v":"value"}," dana"],"many":["za ",{"t":"idOrVar","v":"value"}," dana"],"one":"sutra","other":["za ",{"t":"idOrVar","v":"value"}," dana"],"two":["za ",{"t":"idOrVar","v":"value"}," dana"],"zero":"danas"},"$x":[{"t":"idOrVar","v":"plural"},"value"]},{"$i":"weeks-until-long","$v":{"few":["za ",{"t":"idOrVar","v":"value"}," nedelje/a"],"many":["za ",{"t":"idOrVar","v":"value"}," nedelje/a"],"one":"sledeća nedelja","other":["za ",{"t":"idOrVar","v":"value"}," nedelje/a"],"two":["za ",{"t":"idOrVar","v":"value"}," nedelje/a"],"zero":"ove nedelje"},"$x":[{"t":"idOrVar","v":"plural"},"value"]},{"$i":"months-until-long","$v":{"few":["za ",{"t":"idOrVar","v":"value"}," meseca/i"],"many":["za ",{"t":"idOrVar","v":"value"}," meseca/i"],"one":"sledeći mesec","other":["za ",{"t":"idOrVar","v":"value"}," meseca/i"],"two":["za ",{"t":"idOrVar","v":"value"}," meseca/i"],"zero":"ovog meseca"},"$x":[{"t":"idOrVar","v":"plural"},"value"]},{"$i":"years-until-long","$v":{"few":["za ",{"t":"idOrVar","v":"value"}," godine/a"],"many":["za ",{"t":"idOrVar","v":"value"}," godine/a"],"one":"sledeća godina","other":["za ",{"t":"idOrVar","v":"value"}," godine/a"],"two":["za ",{"t":"idOrVar","v":"value"}," godine/a"],"zero":"ove godine"},"$x":[{"t":"idOrVar","v":"plural"},"value"]},{"$i":"minutes-ago-short","$v":{"other":["Pre ",{"t":"idOrVar","v":"value"}," m"],"zero":"malopre"},"$x":[{"t":"idOrVar","v":"plural"},"value"]},{"$i":"hours-ago-short","$v":{"other":["Pre ",{"t":"idOrVar","v":"value"}," h"],"zero":"malopre"},"$x":[{"t":"idOrVar","v":"plural"},"value"]},{"$i":"days-ago-short","$v":{"other":["Pre ",{"t":"idOrVar","v":"value"}," d"],"zero":"danas"},"$x":[{"t":"idOrVar","v":"plural"},"value"]},{"$i":"minutes-until-short","$v":{"other":["za ",{"t":"idOrVar","v":"value"}," m"],"zero":"sada"},"$x":[{"t":"idOrVar","v":"plural"},"value"]},{"$i":"hours-until-short","$v":{"other":["za ",{"t":"idOrVar","v":"value"}," h"],"zero":"sada"},"$x":[{"t":"idOrVar","v":"plural"},"value"]},{"$i":"days-until-short","$v":{"other":["za ",{"t":"idOrVar","v":"value"}," d"],"zero":"danas"},"$x":[{"t":"idOrVar","v":"plural"},"value"]},{"$i":"incorrectDate","$v":"(netačan datum)"},{"$i":"dateTimeFormat_%c","$v":"%a %b %e %Y %I:%M:%S %p"},{"$i":"dateTimeFormat_%x","$v":"%m/%d/%Y"},{"$i":"dateTimeFormat_%X","$v":"%I:%M:%S %p"},{"$i":"shortTimeFormat","$v":"%I:%M %p"},{"$i":"shortTimeFormat12","$v":"%I:%M %p"},{"$i":"shortTimeFormat24","$v":"%H:%M"},{"$i":"shortDateTimeFormat","$v":"%x %I:%M %p"},{"$i":"weekStartsOnMonday","$v":"0.0"},{"$i":"firstDayOfTheWeek","$v":"1.0"},{"$i":"time_am","$v":"AM"},{"$i":"time_pm","$v":"Posle podne"}]